djangocms_rosetta/__init__.py
djangocms_rosetta/cms_toolbar.py
djangocms_rosetta-0.0.dist-info/DESCRIPTION.rst
djangocms_rosetta-0.0.dist-info/METADATA
djangocms_rosetta-0.0.dist-info/RECORD
djangocms_rosetta-0.0.dist-info/WHEEL
djangocms_rosetta-0.0.dist-info/metadata.json
djangocms_rosetta-0.0.dist-info/top_level.txt
