Metadata-Version: 2.0
Name: djangocms-rosetta
Version: 0.0
Summary: Link to the rosetta interface in the Django CMS Toolbar
Home-page: https://github.com/philippze/djangocms-rosetta
Author: Philipp Zedler
Author-email: philipp@neue-musik.com
License: MIT
Keywords: Django translation rosetta
Platform: UNKNOWN
Requires-Dist: Django (>=1.7)
Requires-Dist: django-cms (>=3.1)
Requires-Dist: django-rosetta (>=0.7)
